llmstack/cli.py
llmstack/config.toml
llmstack/docker-compose.yml
llmstack-0.2.6.dist-info/LICENSE
llmstack-0.2.6.dist-info/METADATA
llmstack-0.2.6.dist-info/WHEEL
llmstack-0.2.6.dist-info/entry_points.txt
llmstack-0.2.6.dist-info/RECORD
