Metadata-Version: 2.1
Name: llmstack
Version: 0.2.6
Summary: Low-code platform to build generative AI apps, chatbots and agents with your data
License: ELv2
Author: Ajay Chintala
Requires-Python: >=3.10,<4
Classifier: License :: Other/Proprietary License
Classifier: Programming Language :: Python :: 3
Classifier: Programming Language :: Python :: 3.10
Classifier: Programming Language :: Python :: 3.11
Classifier: Programming Language :: Python :: 3.12
Provides-Extra: networking
Requires-Dist: channels-redis (>=4.2.0,<5.0.0)
Requires-Dist: cryptography (>=43.0.1,<44.0.0)
Requires-Dist: jsonpath-ng (>=1.6.1,<2.0.0)
Requires-Dist: junos-eznc (>=2.6.8,<3.0.0) ; extra == "networking"
Requires-Dist: python-on-whales (>=0.71.0,<0.72.0)
Requires-Dist: toml (>=0.10.2,<0.11.0)
